MANIFEST.in
README.md
pyproject.toml
setup.cfg
setup.py
versioneer.py
bin/gCache3
bin/gCatalog3
bin/gStarform3
bin/gconv
bin/ginsp
commands/CmdCatalog.py
commands/CmdStarform.py
commands/CmdTraceGas.py
pygad/__init__.py
pygad/_version.py
pygad/environment.py
pygad/mem_debug.py
pygad/tools.py
pygad/C/Makefile
pygad/C/__init__.py
pygad/C/include/Faddeeva.hpp
pygad/C/include/absorption_spectra.hpp
pygad/C/include/binning.hpp
pygad/C/include/binning_disp.hpp
pygad/C/include/eval_sph.hpp
pygad/C/include/fof.hpp
pygad/C/include/general.hpp
pygad/C/include/halo.hpp
pygad/C/include/kernels.hpp
pygad/C/include/looploop.hpp
pygad/C/include/tree.hpp
pygad/C/include/vector_stats.hpp
pygad/C/include/voigt.hpp
pygad/C/src/Faddeeva.cpp
pygad/C/src/absorption_spectra.cpp
pygad/C/src/binning.cpp
pygad/C/src/binning_disp.cpp
pygad/C/src/eval_sph.cpp
pygad/C/src/fof.cpp
pygad/C/src/general.cpp
pygad/C/src/halo.cpp
pygad/C/src/kernels.cpp
pygad/C/src/tree.cpp
pygad/C/src/voigt.cpp
pygad/analysis/__init__.py
pygad/analysis/absorption_spectra.py
pygad/analysis/analysis.py
pygad/analysis/halo.py
pygad/analysis/profiles.py
pygad/analysis/properties.py
pygad/analysis/sph_eval.py
pygad/analysis/vpfit.py
pygad/binning/__init__.py
pygad/binning/cbinning.py
pygad/binning/core.py
pygad/binning/mapping.py
pygad/binning/oneDbinning.py
pygad/cloudy/__init__.py
pygad/cloudy/cloudy_tables.py
pygad/cloudy/treecol.py
pygad/cmdtool/__init__.py
pygad/cmdtool/gCache.py
pygad/config/README.txt
pygad/config/derived.cfg
pygad/config/gadget.cfg
pygad/config/units.cfg
pygad/gadget/__init__.py
pygad/gadget/config.py
pygad/gadget/handler.py
pygad/gadget/lowlevel_file.py
pygad/kernels/__init__.py
pygad/kernels/definitions.py
pygad/kernels/integral.py
pygad/octree/__init__.py
pygad/octree/coctree.py
pygad/octree/octree.py
pygad/physics/__init__.py
pygad/physics/cooling.py
pygad/physics/cosmology.py
pygad/physics/quantities.py
pygad/plotting/__init__.py
pygad/plotting/colormaps.py
pygad/plotting/general.py
pygadmpa.egg-info/PKG-INFO
pygadmpa.egg-info/SOURCES.txt
pygadmpa.egg-info/dependency_links.txt
pygadmpa.egg-info/requires.txt
pygadmpa.egg-info/top_level.txt